ffpb.py
ffprb-0.0.1.dist-info/COPYING
ffprb-0.0.1.dist-info/METADATA
ffprb-0.0.1.dist-info/WHEEL
ffprb-0.0.1.dist-info/entry_points.txt
ffprb-0.0.1.dist-info/top_level.txt
ffprb-0.0.1.dist-info/zip-safe
ffprb-0.0.1.dist-info/RECORD
